aiorobot/__init__.py
aiorobot/driver.py
aiorobot/events.py
aiorobot/protocol.py
aiorobot/robot.py
aiorobot/types.py
aiorobot/examples/__init__.py
aiorobot/examples/callbacks.py
aiorobot/examples/current_events.py
aiorobot/examples/drive.py
aiorobot/examples/listen_events.py
aiorobot/examples/nowait.py
aiorobot/examples/raw.py
aiorobot/examples/simultaneous.py
aiorobot/examples/thread.py
aiorobot-0.3.0.dist-info/METADATA
aiorobot-0.3.0.dist-info/WHEEL
aiorobot-0.3.0.dist-info/top_level.txt
aiorobot-0.3.0.dist-info/RECORD
