Metadata-Version: 2.1
Name: aiorobot
Version: 0.3.0
Summary: asyncio interface for iRobot Root
Home-page: https://github.com/entwanne/aiorobot
Author: entwanne
Author-email: antoine.rozo@gmail.com
License: MIT
Platform: UNKNOWN
Classifier: License :: OSI Approved :: MIT License
Classifier: Programming Language :: Python :: 3
Classifier: Programming Language :: Python :: 3.7
Classifier: Programming Language :: Python :: 3.8
Requires-Dist: bleak
Requires-Dist: crc8
Provides-Extra: build
Requires-Dist: setuptools ; extra == 'build'
Requires-Dist: wheel ; extra == 'build'
Requires-Dist: twine ; extra == 'build'
